MANIFEST.in
README.rst
requirements.txt
setup.cfg
setup.py
djmicrosip_mail/__init__.py
djmicrosip_mail/autocomplete_light_registry.py
djmicrosip_mail/config.py
djmicrosip_mail/core.py
djmicrosip_mail/forms.py
djmicrosip_mail/models.py
djmicrosip_mail/tasks.py
djmicrosip_mail/tests.py
djmicrosip_mail/urls.py
djmicrosip_mail/views.py
djmicrosip_mail.egg-info/PKG-INFO
djmicrosip_mail.egg-info/SOURCES.txt
djmicrosip_mail.egg-info/dependency_links.txt
djmicrosip_mail.egg-info/requires.txt
djmicrosip_mail.egg-info/top_level.txt
djmicrosip_mail/__pycache__/__init__.cpython-37.pyc
djmicrosip_mail/__pycache__/autocomplete_light_registry.cpython-37.pyc
djmicrosip_mail/__pycache__/config.cpython-37.pyc
djmicrosip_mail/__pycache__/core.cpython-37.pyc
djmicrosip_mail/__pycache__/forms.cpython-37.pyc
djmicrosip_mail/__pycache__/models.cpython-37.pyc
djmicrosip_mail/__pycache__/tasks.cpython-37.pyc
djmicrosip_mail/__pycache__/tests.cpython-37.pyc
djmicrosip_mail/__pycache__/urls.cpython-37.pyc
djmicrosip_mail/__pycache__/views.cpython-37.pyc
djmicrosip_mail/modulos/__init__.py
djmicrosip_mail/modulos/__pycache__/__init__.cpython-37.pyc
djmicrosip_mail/modulos/clientes/__init__.py
djmicrosip_mail/modulos/clientes/forms.py
djmicrosip_mail/modulos/clientes/models.py
djmicrosip_mail/modulos/clientes/urls.py
djmicrosip_mail/modulos/clientes/views.py
djmicrosip_mail/modulos/clientes/__pycache__/__init__.cpython-37.pyc
djmicrosip_mail/modulos/clientes/__pycache__/forms.cpython-37.pyc
djmicrosip_mail/modulos/clientes/__pycache__/models.cpython-37.pyc
djmicrosip_mail/modulos/clientes/__pycache__/urls.cpython-37.pyc
djmicrosip_mail/modulos/clientes/__pycache__/views.cpython-37.pyc
djmicrosip_mail/modulos/herramientas/__init__.py
djmicrosip_mail/modulos/herramientas/forms.py
djmicrosip_mail/modulos/herramientas/models.py
djmicrosip_mail/modulos/herramientas/procedures.py
djmicrosip_mail/modulos/herramientas/urls.py
djmicrosip_mail/modulos/herramientas/views.py
djmicrosip_mail/modulos/herramientas/__pycache__/__init__.cpython-37.pyc
djmicrosip_mail/modulos/herramientas/__pycache__/forms.cpython-37.pyc
djmicrosip_mail/modulos/herramientas/__pycache__/models.cpython-37.pyc
